{
    "count": 200,
    "next": "https:\/\/cryptopanic.com\/api\/v1\/posts\/?auth_token=01c356e89ffc1b8eba2127c81fc8c66ee0eace75&kind=news&currencies=IOTX&page=2",
    "previous": null,
    "results": [
        {
            "kind": "news",
            "domain": "@iotex_io",
            "source": {
                "title": "IoTeX Twitter",
                "region": "en",
                "domain": "twitter.com",
                "path": "@iotex_io"
            },
            "title": "2023 is the year of #DePIN.\n\nHear from projects @DIMO_Network, @arkreen_network, @EclipseFND, @hotspotty, and\u2026",
            "published_at": "2023-07-11T23:55:00Z",
            "slug": "2023-is-the-year-of-DePIN-Hear-from-projects-DIMO_Network-arkreen_network-EclipseFND-hotspotty-and",
            "currencies": [
                {
                    "code": "IOTX",
                    "title": "IoTeX",
                    "slug": "iotex",
                    "url": "https:\/\/cryptopanic.com\/news\/iotex\/"
                },
                {
                    "code": "IOTX",
                    "title": "Binance-Peg IoTeX",
                    "slug": "binance-peg-iotex",
                    "url": "https:\/\/cryptopanic.com\/news\/binance-peg-iotex\/"
                },
                {
                    "code": "WIOTX",
                    "title": "Wrapped IoTex",
                    "slug": "wrapped-iotex",
                    "url": "https:\/\/cryptopanic.com\/news\/wrapped-iotex\/"
                },
                {
                    "code": "CIOTX",
                    "title": "Crosschain IOTX",
                    "slug": "crosschain-iotx",
                    "url": "https:\/\/cryptopanic.com\/news\/crosschain-iotx\/"
                }
            ],
            "id": 18765026,
            "url": "https:\/\/cryptopanic.com\/news\/18765026\/2023-is-the-year-of-DePIN-Hear-from-projects-DIMO_Network-arkreen_network-EclipseFND-hotspotty-and",
            "created_at": "2023-07-11T23:55:00Z",
            "votes": {
                "negative": 0,
                "positive": 0,
                "important": 0,
                "liked": 0,
                "disliked": 0,
                "lol": 0,
                "toxic": 0,
                "saved": 0,
                "comments": 0
            }
        },
        {
            "kind": "news",
            "domain": "@iotex_io",
            "votes": {
                "negative": 0,
                "positive": 0,
                "important": 0,
                "liked": 1,
                "disliked": 0,
                "lol": 0,
                "toxic": 0,
                "saved": 0,
                "comments": 1
            },
            "source": {
                "title": "IoTeX Twitter",
                "region": "en",
                "domain": "twitter.com",
                "path": "@iotex_io"
            },
            "title": "Building in a bear market, Web3 has become all about the technology. \n\nHear from the L1&amp;2 brands building the infra\u2026",
            "published_at": "2023-07-11T21:23:26Z",
            "slug": "Building-in-a-bear-market-Web3-has-become-all-about-the-technology-Hear-from-the-L1amp2-brands-building-the-infra",
            "currencies": [
                {
                    "code": "IOTX",
                    "title": "IoTeX",
                    "slug": "iotex",
                    "url": "https:\/\/cryptopanic.com\/news\/iotex\/"
                },
                {
                    "code": "IOTX",
                    "title": "Binance-Peg IoTeX",
                    "slug": "binance-peg-iotex",
                    "url": "https:\/\/cryptopanic.com\/news\/binance-peg-iotex\/"
                },
                {
                    "code": "WIOTX",
                    "title": "Wrapped IoTex",
                    "slug": "wrapped-iotex",
                    "url": "https:\/\/cryptopanic.com\/news\/wrapped-iotex\/"
                },
                {
                    "code": "CIOTX",
                    "title": "Crosschain IOTX",
                    "slug": "crosschain-iotx",
                    "url": "https:\/\/cryptopanic.com\/news\/crosschain-iotx\/"
                }
            ],
            "id": 18765027,
            "url": "https:\/\/cryptopanic.com\/news\/18765027\/Building-in-a-bear-market-Web3-has-become-all-about-the-technology-Hear-from-the-L1amp2-brands-building-the-infra",
            "created_at": "2023-07-11T21:23:26Z"
        },
        {
            "kind": "news",
            "domain": "@iotex_io",
            "source": {
                "title": "IoTeX Twitter",
                "region": "en",
                "domain": "twitter.com",
                "path": "@iotex_io"
            },
            "title": "#DePIN can save lives by providing energy resources when centralized entities fail. \n\n@cat_uccino from\u2026",
            "published_at": "2023-07-10T20:17:27Z",
            "slug": "DePIN-can-save-lives-by-providing-energy-resources-when-centralized-entities-fail-cat_uccino-from",
            "currencies": [
                {
                    "code": "IOTX",
                    "title": "IoTeX",
                    "slug": "iotex",
                    "url": "https:\/\/cryptopanic.com\/news\/iotex\/"
                },
                {
                    "code": "IOTX",
                    "title": "Binance-Peg IoTeX",
                    "slug": "binance-peg-iotex",
                    "url": "https:\/\/cryptopanic.com\/news\/binance-peg-iotex\/"
                },
                {
                    "code": "WIOTX",
                    "title": "Wrapped IoTex",
                    "slug": "wrapped-iotex",
                    "url": "https:\/\/cryptopanic.com\/news\/wrapped-iotex\/"
                },
                {
                    "code": "CIOTX",
                    "title": "Crosschain IOTX",
                    "slug": "crosschain-iotx",
                    "url": "https:\/\/cryptopanic.com\/news\/crosschain-iotx\/"
                }
            ],
            "id": 18756850,
            "url": "https:\/\/cryptopanic.com\/news\/18756850\/DePIN-can-save-lives-by-providing-energy-resources-when-centralized-entities-fail-cat_uccino-from",
            "created_at": "2023-07-10T20:17:27Z",
            "votes": {
                "negative": 0,
                "positive": 0,
                "important": 0,
                "liked": 0,
                "disliked": 0,
                "lol": 0,
                "toxic": 0,
                "saved": 0,
                "comments": 0
            }
        },
        {
            "kind": "news",
            "domain": "@iotex_io",
            "source": {
                "title": "IoTeX Twitter",
                "region": "en",
                "domain": "twitter.com",
                "path": "@iotex_io"
            },
            "title": "Build a decentralized bike-sharing app that rewards eco-friendliness. \ufe0f\n\nSign up for the livestream with\u2026",
            "published_at": "2023-07-10T15:48:12Z",
            "slug": "Build-a-decentralized-bike-sharing-app-that-rewards-eco-friendliness-Sign-up-for-the-livestream-with",
            "currencies": [
                {
                    "code": "IOTX",
                    "title": "IoTeX",
                    "slug": "iotex",
                    "url": "https:\/\/cryptopanic.com\/news\/iotex\/"
                },
                {
                    "code": "IOTX",
                    "title": "Binance-Peg IoTeX",
                    "slug": "binance-peg-iotex",
                    "url": "https:\/\/cryptopanic.com\/news\/binance-peg-iotex\/"
                },
                {
                    "code": "WIOTX",
                    "title": "Wrapped IoTex",
                    "slug": "wrapped-iotex",
                    "url": "https:\/\/cryptopanic.com\/news\/wrapped-iotex\/"
                },
                {
                    "code": "CIOTX",
                    "title": "Crosschain IOTX",
                    "slug": "crosschain-iotx",
                    "url": "https:\/\/cryptopanic.com\/news\/crosschain-iotx\/"
                }
            ],
            "id": 18756851,
            "url": "https:\/\/cryptopanic.com\/news\/18756851\/Build-a-decentralized-bike-sharing-app-that-rewards-eco-friendliness-Sign-up-for-the-livestream-with",
            "created_at": "2023-07-10T15:48:12Z",
            "votes": {
                "negative": 0,
                "positive": 0,
                "important": 0,
                "liked": 0,
                "disliked": 0,
                "lol": 0,
                "toxic": 0,
                "saved": 0,
                "comments": 0
            }
        },
        {
            "kind": "news",
            "domain": "@iotex_io",
            "source": {
                "title": "IoTeX Twitter",
                "region": "en",
                "domain": "twitter.com",
                "path": "@iotex_io"
            },
            "title": "Let's get innovative solutions built on IoTeX at the @IntuOfficial hackathon. Details to join below \u2b07\ufe0f",
            "published_at": "2023-07-07T19:46:06Z",
            "slug": "Lets-get-innovative-solutions-built-on-IoTeX-at-the-IntuOfficial-hackathon-Details-to-join-below",
            "currencies": [
                {
                    "code": "IOTX",
                    "title": "IoTeX",
                    "slug": "iotex",
                    "url": "https:\/\/cryptopanic.com\/news\/iotex\/"
                },
                {
                    "code": "IOTX",
                    "title": "Binance-Peg IoTeX",
                    "slug": "binance-peg-iotex",
                    "url": "https:\/\/cryptopanic.com\/news\/binance-peg-iotex\/"
                },
                {
                    "code": "WIOTX",
                    "title": "Wrapped IoTex",
                    "slug": "wrapped-iotex",
                    "url": "https:\/\/cryptopanic.com\/news\/wrapped-iotex\/"
                },
                {
                    "code": "CIOTX",
                    "title": "Crosschain IOTX",
                    "slug": "crosschain-iotx",
                    "url": "https:\/\/cryptopanic.com\/news\/crosschain-iotx\/"
                }
            ],
            "id": 18740732,
            "url": "https:\/\/cryptopanic.com\/news\/18740732\/Lets-get-innovative-solutions-built-on-IoTeX-at-the-IntuOfficial-hackathon-Details-to-join-below",
            "created_at": "2023-07-07T19:46:06Z",
            "votes": {
                "negative": 0,
                "positive": 0,
                "important": 0,
                "liked": 0,
                "disliked": 0,
                "lol": 0,
                "toxic": 0,
                "saved": 0,
                "comments": 0
            }
        },
        {
            "kind": "news",
            "domain": "@iotex_io",
            "source": {
                "title": "IoTeX Twitter",
                "region": "en",
                "domain": "twitter.com",
                "path": "@iotex_io"
            },
            "title": "We're sponsoring and giving away three Pebble Trackers and ten NFTs for the @TIPIN_PROJECT 1000 event.  \n\nEnter to\u2026",
            "published_at": "2023-07-07T19:31:35Z",
            "slug": "Were-sponsoring-and-giving-away-three-Pebble-Trackers-and-ten-NFTs-for-the-TIPIN_PROJECT-1000-event-Enter-to",
            "currencies": [
                {
                    "code": "IOTX",
                    "title": "IoTeX",
                    "slug": "iotex",
                    "url": "https:\/\/cryptopanic.com\/news\/iotex\/"
                },
                {
                    "code": "IOTX",
                    "title": "Binance-Peg IoTeX",
                    "slug": "binance-peg-iotex",
                    "url": "https:\/\/cryptopanic.com\/news\/binance-peg-iotex\/"
                },
                {
                    "code": "WIOTX",
                    "title": "Wrapped IoTex",
                    "slug": "wrapped-iotex",
                    "url": "https:\/\/cryptopanic.com\/news\/wrapped-iotex\/"
                },
                {
                    "code": "CIOTX",
                    "title": "Crosschain IOTX",
                    "slug": "crosschain-iotx",
                    "url": "https:\/\/cryptopanic.com\/news\/crosschain-iotx\/"
                }
            ],
            "id": 18740733,
            "url": "https:\/\/cryptopanic.com\/news\/18740733\/Were-sponsoring-and-giving-away-three-Pebble-Trackers-and-ten-NFTs-for-the-TIPIN_PROJECT-1000-event-Enter-to",
            "created_at": "2023-07-07T19:31:35Z",
            "votes": {
                "negative": 0,
                "positive": 0,
                "important": 0,
                "liked": 0,
                "disliked": 0,
                "lol": 0,
                "toxic": 0,
                "saved": 0,
                "comments": 0
            }
        },
        {
            "kind": "news",
            "domain": "@iotex_io",
            "source": {
                "title": "IoTeX Twitter",
                "region": "en",
                "domain": "twitter.com",
                "path": "@iotex_io"
            },
            "title": "RT @iotex_dev: What: \"Building a #DePIN project w\/ @w3bstream_com\"\nWhen: July 12th, noon EDT\nWho: @GiupiDeLuca @zimne1 @IntuOfficial @Think\u2026",
            "published_at": "2023-07-07T16:13:42Z",
            "slug": "RT-iotex_dev-What-Building-a-DePIN-project-w-w3bstream_com-When-July-12th-noon-EDT-Who-GiupiDeLuca-zimne1-IntuOfficial-Think",
            "currencies": [
                {
                    "code": "IOTX",
                    "title": "IoTeX",
                    "slug": "iotex",
                    "url": "https:\/\/cryptopanic.com\/news\/iotex\/"
                },
                {
                    "code": "IOTX",
                    "title": "Binance-Peg IoTeX",
                    "slug": "binance-peg-iotex",
                    "url": "https:\/\/cryptopanic.com\/news\/binance-peg-iotex\/"
                },
                {
                    "code": "WIOTX",
                    "title": "Wrapped IoTex",
                    "slug": "wrapped-iotex",
                    "url": "https:\/\/cryptopanic.com\/news\/wrapped-iotex\/"
                },
                {
                    "code": "CIOTX",
                    "title": "Crosschain IOTX",
                    "slug": "crosschain-iotx",
                    "url": "https:\/\/cryptopanic.com\/news\/crosschain-iotx\/"
                }
            ],
            "id": 18740734,
            "url": "https:\/\/cryptopanic.com\/news\/18740734\/RT-iotex_dev-What-Building-a-DePIN-project-w-w3bstream_com-When-July-12th-noon-EDT-Who-GiupiDeLuca-zimne1-IntuOfficial-Think",
            "created_at": "2023-07-07T16:13:42Z",
            "votes": {
                "negative": 0,
                "positive": 0,
                "important": 0,
                "liked": 0,
                "disliked": 0,
                "lol": 0,
                "toxic": 0,
                "saved": 0,
                "comments": 0
            }
        },
        {
            "kind": "news",
            "domain": "@iotex_io",
            "source": {
                "title": "IoTeX Twitter",
                "region": "en",
                "domain": "twitter.com",
                "path": "@iotex_io"
            },
            "title": "RT @IOSGVC: Stoked to announce IOSG as a proud partner of the #R3alWorld at #EthCC, hosted by @iotex_io \n\nJoin us as we dive into the vibra\u2026",
            "published_at": "2023-07-07T14:27:17Z",
            "slug": "RT-IOSGVC-Stoked-to-announce-IOSG-as-a-proud-partner-of-the-R3alWorld-at-EthCC-hosted-by-iotex_io-Join-us-as-we-dive-into-the-vibra",
            "currencies": [
                {
                    "code": "IOTX",
                    "title": "IoTeX",
                    "slug": "iotex",
                    "url": "https:\/\/cryptopanic.com\/news\/iotex\/"
                },
                {
                    "code": "IOTX",
                    "title": "Binance-Peg IoTeX",
                    "slug": "binance-peg-iotex",
                    "url": "https:\/\/cryptopanic.com\/news\/binance-peg-iotex\/"
                },
                {
                    "code": "WIOTX",
                    "title": "Wrapped IoTex",
                    "slug": "wrapped-iotex",
                    "url": "https:\/\/cryptopanic.com\/news\/wrapped-iotex\/"
                },
                {
                    "code": "CIOTX",
                    "title": "Crosschain IOTX",
                    "slug": "crosschain-iotx",
                    "url": "https:\/\/cryptopanic.com\/news\/crosschain-iotx\/"
                }
            ],
            "id": 18740735,
            "url": "https:\/\/cryptopanic.com\/news\/18740735\/RT-IOSGVC-Stoked-to-announce-IOSG-as-a-proud-partner-of-the-R3alWorld-at-EthCC-hosted-by-iotex_io-Join-us-as-we-dive-into-the-vibra",
            "created_at": "2023-07-07T14:27:17Z",
            "votes": {
                "negative": 0,
                "positive": 0,
                "important": 0,
                "liked": 0,
                "disliked": 0,
                "lol": 0,
                "toxic": 0,
                "saved": 0,
                "comments": 0
            }
        },
        {
            "kind": "news",
            "domain": "@iotex_io",
            "source": {
                "title": "IoTeX Twitter",
                "region": "en",
                "domain": "twitter.com",
                "path": "@iotex_io"
            },
            "title": "Welcome @borderless_cap and @IOSGVC to the sponsors bringing #R3alWorld to @EthCC.\n\nSpots are filling up for the bi\u2026",
            "published_at": "2023-07-06T21:34:18Z",
            "slug": "Welcome-borderless_cap-and-IOSGVC-to-the-sponsors-bringing-R3alWorld-to-EthCC-Spots-are-filling-up-for-the-bi",
            "currencies": [
                {
                    "code": "IOTX",
                    "title": "IoTeX",
                    "slug": "iotex",
                    "url": "https:\/\/cryptopanic.com\/news\/iotex\/"
                },
                {
                    "code": "IOTX",
                    "title": "Binance-Peg IoTeX",
                    "slug": "binance-peg-iotex",
                    "url": "https:\/\/cryptopanic.com\/news\/binance-peg-iotex\/"
                },
                {
                    "code": "WIOTX",
                    "title": "Wrapped IoTex",
                    "slug": "wrapped-iotex",
                    "url": "https:\/\/cryptopanic.com\/news\/wrapped-iotex\/"
                },
                {
                    "code": "CIOTX",
                    "title": "Crosschain IOTX",
                    "slug": "crosschain-iotx",
                    "url": "https:\/\/cryptopanic.com\/news\/crosschain-iotx\/"
                }
            ],
            "id": 18733146,
            "url": "https:\/\/cryptopanic.com\/news\/18733146\/Welcome-borderless_cap-and-IOSGVC-to-the-sponsors-bringing-R3alWorld-to-EthCC-Spots-are-filling-up-for-the-bi",
            "created_at": "2023-07-06T21:34:18Z",
            "votes": {
                "negative": 0,
                "positive": 0,
                "important": 0,
                "liked": 0,
                "disliked": 0,
                "lol": 0,
                "toxic": 0,
                "saved": 0,
                "comments": 0
            }
        },
        {
            "kind": "news",
            "domain": "@iotex_io",
            "source": {
                "title": "IoTeX Twitter",
                "region": "en",
                "domain": "twitter.com",
                "path": "@iotex_io"
            },
            "title": "zk-proofs X DePIN.\n\nHear about @SpaceandTimeDB's novel zk-proof of SQL, #DePIN's potential to change lives, and mor\u2026",
            "published_at": "2023-07-06T16:33:42Z",
            "slug": "zk-proofs-X-DePIN-Hear-about-SpaceandTimeDBs-novel-zk-proof-of-SQL-DePINs-potential-to-change-lives-and-mor",
            "currencies": [
                {
                    "code": "IOTX",
                    "title": "IoTeX",
                    "slug": "iotex",
                    "url": "https:\/\/cryptopanic.com\/news\/iotex\/"
                },
                {
                    "code": "IOTX",
                    "title": "Binance-Peg IoTeX",
                    "slug": "binance-peg-iotex",
                    "url": "https:\/\/cryptopanic.com\/news\/binance-peg-iotex\/"
                },
                {
                    "code": "WIOTX",
                    "title": "Wrapped IoTex",
                    "slug": "wrapped-iotex",
                    "url": "https:\/\/cryptopanic.com\/news\/wrapped-iotex\/"
                },
                {
                    "code": "CIOTX",
                    "title": "Crosschain IOTX",
                    "slug": "crosschain-iotx",
                    "url": "https:\/\/cryptopanic.com\/news\/crosschain-iotx\/"
                }
            ],
            "id": 18733147,
            "url": "https:\/\/cryptopanic.com\/news\/18733147\/zk-proofs-X-DePIN-Hear-about-SpaceandTimeDBs-novel-zk-proof-of-SQL-DePINs-potential-to-change-lives-and-mor",
            "created_at": "2023-07-06T16:33:42Z",
            "votes": {
                "negative": 0,
                "positive": 0,
                "important": 0,
                "liked": 0,
                "disliked": 0,
                "lol": 0,
                "toxic": 0,
                "saved": 0,
                "comments": 0
            }
        },
        {
            "kind": "news",
            "domain": "@iotex_io",
            "source": {
                "title": "IoTeX Twitter",
                "region": "en",
                "domain": "twitter.com",
                "path": "@iotex_io"
            },
            "title": "v1.11.0 hardfork activates July 20 on loTeX mainnet \ufe0f\n\nAll nodes must upgrade to the latest &amp; genesis.\u2026",
            "published_at": "2023-07-05T23:40:46Z",
            "slug": "v1110-hardfork-activates-July-20-on-loTeX-mainnet-All-nodes-must-upgrade-to-the-latest-amp-genesis",
            "currencies": [
                {
                    "code": "IOTX",
                    "title": "IoTeX",
                    "slug": "iotex",
                    "url": "https:\/\/cryptopanic.com\/news\/iotex\/"
                },
                {
                    "code": "IOTX",
                    "title": "Binance-Peg IoTeX",
                    "slug": "binance-peg-iotex",
                    "url": "https:\/\/cryptopanic.com\/news\/binance-peg-iotex\/"
                },
                {
                    "code": "WIOTX",
                    "title": "Wrapped IoTex",
                    "slug": "wrapped-iotex",
                    "url": "https:\/\/cryptopanic.com\/news\/wrapped-iotex\/"
                },
                {
                    "code": "CIOTX",
                    "title": "Crosschain IOTX",
                    "slug": "crosschain-iotx",
                    "url": "https:\/\/cryptopanic.com\/news\/crosschain-iotx\/"
                }
            ],
            "id": 18724678,
            "url": "https:\/\/cryptopanic.com\/news\/18724678\/v1110-hardfork-activates-July-20-on-loTeX-mainnet-All-nodes-must-upgrade-to-the-latest-amp-genesis",
            "created_at": "2023-07-05T23:40:46Z",
            "votes": {
                "negative": 0,
                "positive": 0,
                "important": 0,
                "liked": 0,
                "disliked": 0,
                "lol": 0,
                "toxic": 0,
                "saved": 0,
                "comments": 0
            }
        },
        {
            "kind": "news",
            "domain": "@iotex_io",
            "source": {
                "title": "IoTeX Twitter",
                "region": "en",
                "domain": "twitter.com",
                "path": "@iotex_io"
            },
            "title": "RT @EclipseFND: Going to ETH CC? We are excited to be co-hosting R3alWorld alongside @iotex_io and @SamsungNext\n\nParis. July 16th.\n\nA full\u2026",
            "published_at": "2023-07-05T17:57:09Z",
            "slug": "RT-EclipseFND-Going-to-ETH-CC-We-are-excited-to-be-co-hosting-R3alWorld-alongside-iotex_io-and-SamsungNext-Paris-July-16th-A-full",
            "currencies": [
                {
                    "code": "IOTX",
                    "title": "IoTeX",
                    "slug": "iotex",
                    "url": "https:\/\/cryptopanic.com\/news\/iotex\/"
                },
                {
                    "code": "IOTX",
                    "title": "Binance-Peg IoTeX",
                    "slug": "binance-peg-iotex",
                    "url": "https:\/\/cryptopanic.com\/news\/binance-peg-iotex\/"
                },
                {
                    "code": "WIOTX",
                    "title": "Wrapped IoTex",
                    "slug": "wrapped-iotex",
                    "url": "https:\/\/cryptopanic.com\/news\/wrapped-iotex\/"
                },
                {
                    "code": "CIOTX",
                    "title": "Crosschain IOTX",
                    "slug": "crosschain-iotx",
                    "url": "https:\/\/cryptopanic.com\/news\/crosschain-iotx\/"
                }
            ],
            "id": 18724679,
            "url": "https:\/\/cryptopanic.com\/news\/18724679\/RT-EclipseFND-Going-to-ETH-CC-We-are-excited-to-be-co-hosting-R3alWorld-alongside-iotex_io-and-SamsungNext-Paris-July-16th-A-full",
            "created_at": "2023-07-05T17:57:09Z",
            "votes": {
                "negative": 0,
                "positive": 0,
                "important": 0,
                "liked": 0,
                "disliked": 0,
                "lol": 0,
                "toxic": 0,
                "saved": 0,
                "comments": 0
            }
        },
        {
            "kind": "news",
            "domain": "@iotex_io",
            "source": {
                "title": "IoTeX Twitter",
                "region": "en",
                "domain": "twitter.com",
                "path": "@iotex_io"
            },
            "title": "Enter the @iotex_io X @Port3Network NFT giveaway to celebrate our partnership.\n\n\u23f0 July 5th, 11am PST to July 12th,\u2026",
            "published_at": "2023-07-05T17:08:16Z",
            "slug": "Enter-the-iotex_io-X-Port3Network-NFT-giveaway-to-celebrate-our-partnership-July-5th-11am-PST-to-July-12th",
            "currencies": [
                {
                    "code": "IOTX",
                    "title": "IoTeX",
                    "slug": "iotex",
                    "url": "https:\/\/cryptopanic.com\/news\/iotex\/"
                },
                {
                    "code": "IOTX",
                    "title": "Binance-Peg IoTeX",
                    "slug": "binance-peg-iotex",
                    "url": "https:\/\/cryptopanic.com\/news\/binance-peg-iotex\/"
                },
                {
                    "code": "WIOTX",
                    "title": "Wrapped IoTex",
                    "slug": "wrapped-iotex",
                    "url": "https:\/\/cryptopanic.com\/news\/wrapped-iotex\/"
                },
                {
                    "code": "CIOTX",
                    "title": "Crosschain IOTX",
                    "slug": "crosschain-iotx",
                    "url": "https:\/\/cryptopanic.com\/news\/crosschain-iotx\/"
                }
            ],
            "id": 18724680,
            "url": "https:\/\/cryptopanic.com\/news\/18724680\/Enter-the-iotex_io-X-Port3Network-NFT-giveaway-to-celebrate-our-partnership-July-5th-11am-PST-to-July-12th",
            "created_at": "2023-07-05T17:08:16Z",
            "votes": {
                "negative": 0,
                "positive": 0,
                "important": 0,
                "liked": 0,
                "disliked": 0,
                "lol": 0,
                "toxic": 0,
                "saved": 0,
                "comments": 0
            }
        },
        {
            "kind": "news",
            "domain": "@iotex_io",
            "source": {
                "title": "IoTeX Twitter",
                "region": "en",
                "domain": "twitter.com",
                "path": "@iotex_io"
            },
            "title": "#DePIN hardware is the new mining machine.\n\n@BiancaYijiaChen from @Global_JDI on #R3alTalk.",
            "published_at": "2023-07-05T16:34:03Z",
            "slug": "DePIN-hardware-is-the-new-mining-machine-BiancaYijiaChen-from-Global_JDI-on-R3alTalk",
            "currencies": [
                {
                    "code": "IOTX",
                    "title": "IoTeX",
                    "slug": "iotex",
                    "url": "https:\/\/cryptopanic.com\/news\/iotex\/"
                },
                {
                    "code": "IOTX",
                    "title": "Binance-Peg IoTeX",
                    "slug": "binance-peg-iotex",
                    "url": "https:\/\/cryptopanic.com\/news\/binance-peg-iotex\/"
                },
                {
                    "code": "WIOTX",
                    "title": "Wrapped IoTex",
                    "slug": "wrapped-iotex",
                    "url": "https:\/\/cryptopanic.com\/news\/wrapped-iotex\/"
                },
                {
                    "code": "CIOTX",
                    "title": "Crosschain IOTX",
                    "slug": "crosschain-iotx",
                    "url": "https:\/\/cryptopanic.com\/news\/crosschain-iotx\/"
                }
            ],
            "id": 18724681,
            "url": "https:\/\/cryptopanic.com\/news\/18724681\/DePIN-hardware-is-the-new-mining-machine-BiancaYijiaChen-from-Global_JDI-on-R3alTalk",
            "created_at": "2023-07-05T16:34:03Z",
            "votes": {
                "negative": 0,
                "positive": 0,
                "important": 0,
                "liked": 0,
                "disliked": 0,
                "lol": 0,
                "toxic": 0,
                "saved": 0,
                "comments": 0
            }
        },
        {
            "kind": "news",
            "domain": "@iotex_io",
            "source": {
                "title": "IoTeX Twitter",
                "region": "en",
                "domain": "twitter.com",
                "path": "@iotex_io"
            },
            "title": "#R3alWorld is your ticket into the $3.5 trillion dollar market future of the #DePIN sector.\n\nLess than two weeks aw\u2026",
            "published_at": "2023-07-05T15:56:24Z",
            "slug": "R3alWorld-is-your-ticket-into-the-35-trillion-dollar-market-future-of-the-DePIN-sector-Less-than-two-weeks-aw",
            "currencies": [
                {
                    "code": "IOTX",
                    "title": "IoTeX",
                    "slug": "iotex",
                    "url": "https:\/\/cryptopanic.com\/news\/iotex\/"
                },
                {
                    "code": "IOTX",
                    "title": "Binance-Peg IoTeX",
                    "slug": "binance-peg-iotex",
                    "url": "https:\/\/cryptopanic.com\/news\/binance-peg-iotex\/"
                },
                {
                    "code": "WIOTX",
                    "title": "Wrapped IoTex",
                    "slug": "wrapped-iotex",
                    "url": "https:\/\/cryptopanic.com\/news\/wrapped-iotex\/"
                },
                {
                    "code": "CIOTX",
                    "title": "Crosschain IOTX",
                    "slug": "crosschain-iotx",
                    "url": "https:\/\/cryptopanic.com\/news\/crosschain-iotx\/"
                }
            ],
            "id": 18724682,
            "url": "https:\/\/cryptopanic.com\/news\/18724682\/R3alWorld-is-your-ticket-into-the-35-trillion-dollar-market-future-of-the-DePIN-sector-Less-than-two-weeks-aw",
            "created_at": "2023-07-05T15:56:24Z",
            "votes": {
                "negative": 0,
                "positive": 0,
                "important": 0,
                "liked": 0,
                "disliked": 0,
                "lol": 0,
                "toxic": 0,
                "saved": 0,
                "comments": 0
            }
        },
        {
            "kind": "news",
            "domain": "@iotex_io",
            "source": {
                "title": "IoTeX Twitter",
                "region": "en",
                "domain": "twitter.com",
                "path": "@iotex_io"
            },
            "title": "RT @borderless_cap: Borderless is sponsoring @iotex_io R3al World event in Paris. \n\nIf you want to learn more about the hottest area in Web\u2026",
            "published_at": "2023-07-05T14:45:54Z",
            "slug": "RT-borderless_cap-Borderless-is-sponsoring-iotex_io-R3al-World-event-in-Paris-If-you-want-to-learn-more-about-the-hottest-area-in-Web",
            "currencies": [
                {
                    "code": "IOTX",
                    "title": "IoTeX",
                    "slug": "iotex",
                    "url": "https:\/\/cryptopanic.com\/news\/iotex\/"
                },
                {
                    "code": "IOTX",
                    "title": "Binance-Peg IoTeX",
                    "slug": "binance-peg-iotex",
                    "url": "https:\/\/cryptopanic.com\/news\/binance-peg-iotex\/"
                },
                {
                    "code": "WIOTX",
                    "title": "Wrapped IoTex",
                    "slug": "wrapped-iotex",
                    "url": "https:\/\/cryptopanic.com\/news\/wrapped-iotex\/"
                },
                {
                    "code": "CIOTX",
                    "title": "Crosschain IOTX",
                    "slug": "crosschain-iotx",
                    "url": "https:\/\/cryptopanic.com\/news\/crosschain-iotx\/"
                }
            ],
            "id": 18724683,
            "url": "https:\/\/cryptopanic.com\/news\/18724683\/RT-borderless_cap-Borderless-is-sponsoring-iotex_io-R3al-World-event-in-Paris-If-you-want-to-learn-more-about-the-hottest-area-in-Web",
            "created_at": "2023-07-05T14:45:54Z",
            "votes": {
                "negative": 0,
                "positive": 0,
                "important": 0,
                "liked": 0,
                "disliked": 0,
                "lol": 0,
                "toxic": 0,
                "saved": 0,
                "comments": 0
            }
        },
        {
            "kind": "news",
            "domain": "@iotex_io",
            "source": {
                "title": "IoTeX Twitter",
                "region": "en",
                "domain": "twitter.com",
                "path": "@iotex_io"
            },
            "title": "Hey DePIN builders! \u200d\ud83e\uddd1\u200d\u200d\n\nPaper submissions are due on July 23rd for the First International #DePIN Workshop,\u2026",
            "published_at": "2023-07-03T22:14:18Z",
            "slug": "Hey-DePIN-builders-Paper-submissions-are-due-on-July-23rd-for-the-First-International-DePIN-Workshop",
            "currencies": [
                {
                    "code": "IOTX",
                    "title": "IoTeX",
                    "slug": "iotex",
                    "url": "https:\/\/cryptopanic.com\/news\/iotex\/"
                },
                {
                    "code": "IOTX",
                    "title": "Binance-Peg IoTeX",
                    "slug": "binance-peg-iotex",
                    "url": "https:\/\/cryptopanic.com\/news\/binance-peg-iotex\/"
                },
                {
                    "code": "WIOTX",
                    "title": "Wrapped IoTex",
                    "slug": "wrapped-iotex",
                    "url": "https:\/\/cryptopanic.com\/news\/wrapped-iotex\/"
                },
                {
                    "code": "CIOTX",
                    "title": "Crosschain IOTX",
                    "slug": "crosschain-iotx",
                    "url": "https:\/\/cryptopanic.com\/news\/crosschain-iotx\/"
                }
            ],
            "id": 18709663,
            "url": "https:\/\/cryptopanic.com\/news\/18709663\/Hey-DePIN-builders-Paper-submissions-are-due-on-July-23rd-for-the-First-International-DePIN-Workshop",
            "created_at": "2023-07-03T22:14:18Z",
            "votes": {
                "negative": 0,
                "positive": 0,
                "important": 0,
                "liked": 0,
                "disliked": 0,
                "lol": 0,
                "toxic": 0,
                "saved": 0,
                "comments": 0
            }
        },
        {
            "kind": "news",
            "domain": "@iotex_io",
            "source": {
                "title": "IoTeX Twitter",
                "region": "en",
                "domain": "twitter.com",
                "path": "@iotex_io"
            },
            "title": "Blockchain-powered, tamper-proof hardware is the foundation of #DePIN. \n\nHear from @BiancaYijiaChen of @Global_JDI\u2026",
            "published_at": "2023-07-03T21:09:35Z",
            "slug": "Blockchain-powered-tamper-proof-hardware-is-the-foundation-of-DePIN-Hear-from-BiancaYijiaChen-of-Global_JDI",
            "currencies": [
                {
                    "code": "IOTX",
                    "title": "IoTeX",
                    "slug": "iotex",
                    "url": "https:\/\/cryptopanic.com\/news\/iotex\/"
                },
                {
                    "code": "IOTX",
                    "title": "Binance-Peg IoTeX",
                    "slug": "binance-peg-iotex",
                    "url": "https:\/\/cryptopanic.com\/news\/binance-peg-iotex\/"
                },
                {
                    "code": "WIOTX",
                    "title": "Wrapped IoTex",
                    "slug": "wrapped-iotex",
                    "url": "https:\/\/cryptopanic.com\/news\/wrapped-iotex\/"
                },
                {
                    "code": "CIOTX",
                    "title": "Crosschain IOTX",
                    "slug": "crosschain-iotx",
                    "url": "https:\/\/cryptopanic.com\/news\/crosschain-iotx\/"
                }
            ],
            "id": 18709664,
            "url": "https:\/\/cryptopanic.com\/news\/18709664\/Blockchain-powered-tamper-proof-hardware-is-the-foundation-of-DePIN-Hear-from-BiancaYijiaChen-of-Global_JDI",
            "created_at": "2023-07-03T21:09:35Z",
            "votes": {
                "negative": 0,
                "positive": 0,
                "important": 0,
                "liked": 0,
                "disliked": 0,
                "lol": 0,
                "toxic": 0,
                "saved": 0,
                "comments": 0
            }
        },
        {
            "kind": "news",
            "domain": "@iotex_io",
            "source": {
                "title": "IoTeX Twitter",
                "region": "en",
                "domain": "twitter.com",
                "path": "@iotex_io"
            },
            "title": "20,000+ connected devices across 70+ countries on the IoTeX network. \n\nMarking the halfway point of 2023 with a ma\u2026",
            "published_at": "2023-07-03T20:40:20Z",
            "slug": "20000-connected-devices-across-70-countries-on-the-IoTeX-network-Marking-the-halfway-point-of-2023-with-a-ma",
            "currencies": [
                {
                    "code": "IOTX",
                    "title": "IoTeX",
                    "slug": "iotex",
                    "url": "https:\/\/cryptopanic.com\/news\/iotex\/"
                },
                {
                    "code": "IOTX",
                    "title": "Binance-Peg IoTeX",
                    "slug": "binance-peg-iotex",
                    "url": "https:\/\/cryptopanic.com\/news\/binance-peg-iotex\/"
                },
                {
                    "code": "WIOTX",
                    "title": "Wrapped IoTex",
                    "slug": "wrapped-iotex",
                    "url": "https:\/\/cryptopanic.com\/news\/wrapped-iotex\/"
                },
                {
                    "code": "CIOTX",
                    "title": "Crosschain IOTX",
                    "slug": "crosschain-iotx",
                    "url": "https:\/\/cryptopanic.com\/news\/crosschain-iotx\/"
                }
            ],
            "id": 18709665,
            "url": "https:\/\/cryptopanic.com\/news\/18709665\/20000-connected-devices-across-70-countries-on-the-IoTeX-network-Marking-the-halfway-point-of-2023-with-a-ma",
            "created_at": "2023-07-03T20:40:20Z",
            "votes": {
                "negative": 0,
                "positive": 0,
                "important": 0,
                "liked": 0,
                "disliked": 0,
                "lol": 0,
                "toxic": 0,
                "saved": 0,
                "comments": 0
            }
        },
        {
            "kind": "news",
            "domain": "@iotex_io",
            "source": {
                "title": "IoTeX Twitter",
                "region": "en",
                "domain": "twitter.com",
                "path": "@iotex_io"
            },
            "title": " DePIN Infras\n \u2514 IoTeX\n   \u2514 W3bstream use cases\n     \u2514 Folder too large to open\n\nExplore the myriad of\u2026",
            "published_at": "2023-06-30T20:05:14Z",
            "slug": "DePIN-Infras-IoTeX-W3bstream-use-cases-Folder-too-large-to-open-Explore-the-myriad-of",
            "currencies": [
                {
                    "code": "IOTX",
                    "title": "IoTeX",
                    "slug": "iotex",
                    "url": "https:\/\/cryptopanic.com\/news\/iotex\/"
                },
                {
                    "code": "IOTX",
                    "title": "Binance-Peg IoTeX",
                    "slug": "binance-peg-iotex",
                    "url": "https:\/\/cryptopanic.com\/news\/binance-peg-iotex\/"
                },
                {
                    "code": "WIOTX",
                    "title": "Wrapped IoTex",
                    "slug": "wrapped-iotex",
                    "url": "https:\/\/cryptopanic.com\/news\/wrapped-iotex\/"
                },
                {
                    "code": "CIOTX",
                    "title": "Crosschain IOTX",
                    "slug": "crosschain-iotx",
                    "url": "https:\/\/cryptopanic.com\/news\/crosschain-iotx\/"
                }
            ],
            "id": 18694020,
            "url": "https:\/\/cryptopanic.com\/news\/18694020\/DePIN-Infras-IoTeX-W3bstream-use-cases-Folder-too-large-to-open-Explore-the-myriad-of",
            "created_at": "2023-06-30T20:05:14Z",
            "votes": {
                "negative": 0,
                "positive": 0,
                "important": 0,
                "liked": 0,
                "disliked": 0,
                "lol": 0,
                "toxic": 0,
                "saved": 0,
                "comments": 0
            }
        }
    ]
}
