{
    "count": 200,
    "next": "https:\/\/cryptopanic.com\/api\/v1\/posts\/?auth_token=01c356e89ffc1b8eba2127c81fc8c66ee0eace75&kind=news&currencies=FLOKI&page=2",
    "previous": null,
    "results": [
        {
            "kind": "news",
            "domain": "@RealFlokiInu",
            "source": {
                "title": "Floki Inu Twitter",
                "region": "en",
                "domain": "twitter.com",
                "path": "@realflokiinu"
            },
            "title": "$FLOKI just got listed on BTCC! \ufe0f\ufe0f\n\n#Floki was listed alongside top cryptocurrencies like $MKR and $AGIX. It is al\u2026",
            "published_at": "2023-07-11T15:54:59Z",
            "slug": "FLOKI-just-got-listed-on-BTCC-Floki-was-listed-alongside-top-cryptocurrencies-like-MKR-and-AGIX-It-is-al",
            "currencies": [
                {
                    "code": "FLOKI",
                    "title": "Floki Inu",
                    "slug": null,
                    "url": "https:\/\/cryptopanic.com\/news\/None\/"
                },
                {
                    "code": "FLOKI",
                    "title": "FLOKI",
                    "slug": "floki",
                    "url": "https:\/\/cryptopanic.com\/news\/floki\/"
                },
                {
                    "code": "MKR",
                    "title": "Maker",
                    "slug": "maker",
                    "url": "https:\/\/cryptopanic.com\/news\/maker\/"
                }
            ],
            "id": 18764288,
            "url": "https:\/\/cryptopanic.com\/news\/18764288\/FLOKI-just-got-listed-on-BTCC-Floki-was-listed-alongside-top-cryptocurrencies-like-MKR-and-AGIX-It-is-al",
            "created_at": "2023-07-11T15:54:59Z",
            "votes": {
                "negative": 0,
                "positive": 0,
                "important": 0,
                "liked": 0,
                "disliked": 0,
                "lol": 0,
                "toxic": 0,
                "saved": 0,
                "comments": 0
            }
        },
        {
            "kind": "news",
            "domain": "@RealFlokiInu",
            "source": {
                "title": "Floki Inu Twitter",
                "region": "en",
                "domain": "twitter.com",
                "path": "@realflokiinu"
            },
            "title": "UPDATE: $FLOKI isn't trending on Twitter today. Instead, #Valhalla is stealing the spotlight! \n\nValhalla is #Floki\u2026",
            "published_at": "2023-07-11T15:20:43Z",
            "slug": "UPDATE-FLOKI-isnt-trending-on-Twitter-today-Instead-Valhalla-is-stealing-the-spotlight-Valhalla-is-Floki",
            "currencies": [
                {
                    "code": "FLOKI",
                    "title": "Floki Inu",
                    "slug": null,
                    "url": "https:\/\/cryptopanic.com\/news\/None\/"
                },
                {
                    "code": "FLOKI",
                    "title": "FLOKI",
                    "slug": "floki",
                    "url": "https:\/\/cryptopanic.com\/news\/floki\/"
                }
            ],
            "id": 18764289,
            "url": "https:\/\/cryptopanic.com\/news\/18764289\/UPDATE-FLOKI-isnt-trending-on-Twitter-today-Instead-Valhalla-is-stealing-the-spotlight-Valhalla-is-Floki",
            "created_at": "2023-07-11T15:20:43Z",
            "votes": {
                "negative": 0,
                "positive": 0,
                "important": 0,
                "liked": 0,
                "disliked": 0,
                "lol": 0,
                "toxic": 0,
                "saved": 0,
                "comments": 0
            }
        },
        {
            "kind": "news",
            "domain": "@RealFlokiInu",
            "source": {
                "title": "Floki Inu Twitter",
                "region": "en",
                "domain": "twitter.com",
                "path": "@realflokiinu"
            },
            "title": "#Valhalla has just welcomed a new member to the Vera family: Say hello to Igby!\n\nIn this video, we'll take a close\u2026",
            "published_at": "2023-07-11T12:53:07Z",
            "slug": "Valhalla-has-just-welcomed-a-new-member-to-the-Vera-family-Say-hello-to-Igby-In-this-video-well-take-a-close",
            "currencies": [
                {
                    "code": "FLOKI",
                    "title": "Floki Inu",
                    "slug": null,
                    "url": "https:\/\/cryptopanic.com\/news\/None\/"
                },
                {
                    "code": "FLOKI",
                    "title": "FLOKI",
                    "slug": "floki",
                    "url": "https:\/\/cryptopanic.com\/news\/floki\/"
                }
            ],
            "id": 18764290,
            "url": "https:\/\/cryptopanic.com\/news\/18764290\/Valhalla-has-just-welcomed-a-new-member-to-the-Vera-family-Say-hello-to-Igby-In-this-video-well-take-a-close",
            "created_at": "2023-07-11T12:53:07Z",
            "votes": {
                "negative": 0,
                "positive": 0,
                "important": 0,
                "liked": 0,
                "disliked": 0,
                "lol": 0,
                "toxic": 0,
                "saved": 0,
                "comments": 0
            }
        },
        {
            "kind": "news",
            "domain": "@RealFlokiInu",
            "source": {
                "title": "Floki Inu Twitter",
                "region": "en",
                "domain": "twitter.com",
                "path": "@realflokiinu"
            },
            "title": "Goin' to #Valhalla with #Floki \n\nHear the latest Valhalla news, $FLOKI updates, and have all your questions answere\u2026",
            "published_at": "2023-07-11T09:22:16Z",
            "slug": "Goin-to-Valhalla-with-Floki-Hear-the-latest-Valhalla-news-FLOKI-updates-and-have-all-your-questions-answere",
            "currencies": [
                {
                    "code": "FLOKI",
                    "title": "Floki Inu",
                    "slug": null,
                    "url": "https:\/\/cryptopanic.com\/news\/None\/"
                },
                {
                    "code": "FLOKI",
                    "title": "FLOKI",
                    "slug": "floki",
                    "url": "https:\/\/cryptopanic.com\/news\/floki\/"
                }
            ],
            "id": 18764291,
            "url": "https:\/\/cryptopanic.com\/news\/18764291\/Goin-to-Valhalla-with-Floki-Hear-the-latest-Valhalla-news-FLOKI-updates-and-have-all-your-questions-answere",
            "created_at": "2023-07-11T09:22:16Z",
            "votes": {
                "negative": 0,
                "positive": 0,
                "important": 0,
                "liked": 0,
                "disliked": 0,
                "lol": 0,
                "toxic": 0,
                "saved": 0,
                "comments": 0
            }
        },
        {
            "kind": "news",
            "domain": "@RealFlokiInu",
            "source": {
                "title": "Floki Inu Twitter",
                "region": "en",
                "domain": "twitter.com",
                "path": "@realflokiinu"
            },
            "title": "RT @kucoincom:  What altcoin are you most bullish on?",
            "published_at": "2023-07-11T05:11:24Z",
            "slug": "RT-kucoincom-What-altcoin-are-you-most-bullish-on",
            "currencies": [
                {
                    "code": "FLOKI",
                    "title": "Floki Inu",
                    "slug": null,
                    "url": "https:\/\/cryptopanic.com\/news\/None\/"
                },
                {
                    "code": "FLOKI",
                    "title": "FLOKI",
                    "slug": "floki",
                    "url": "https:\/\/cryptopanic.com\/news\/floki\/"
                }
            ],
            "id": 18756184,
            "url": "https:\/\/cryptopanic.com\/news\/18756184\/RT-kucoincom-What-altcoin-are-you-most-bullish-on",
            "created_at": "2023-07-11T05:11:24Z",
            "votes": {
                "negative": 0,
                "positive": 0,
                "important": 0,
                "liked": 0,
                "disliked": 0,
                "lol": 0,
                "toxic": 0,
                "saved": 0,
                "comments": 0
            }
        },
        {
            "kind": "news",
            "domain": "@RealFlokiInu",
            "source": {
                "title": "Floki Inu Twitter",
                "region": "en",
                "domain": "twitter.com",
                "path": "@realflokiinu"
            },
            "title": "Congratz to the following winners of the #KingsLeague giveaway:\n\n@YOmZ7cfZ9nqFu09\n@astro_pixell\n@Mis_iggyminaj\u2026",
            "published_at": "2023-07-10T14:51:06Z",
            "slug": "Congratz-to-the-following-winners-of-the-KingsLeague-giveaway-YOmZ7cfZ9nqFu09-astro_pixell-Mis_iggyminaj",
            "currencies": [
                {
                    "code": "FLOKI",
                    "title": "Floki Inu",
                    "slug": null,
                    "url": "https:\/\/cryptopanic.com\/news\/None\/"
                },
                {
                    "code": "FLOKI",
                    "title": "FLOKI",
                    "slug": "floki",
                    "url": "https:\/\/cryptopanic.com\/news\/floki\/"
                }
            ],
            "id": 18756185,
            "url": "https:\/\/cryptopanic.com\/news\/18756185\/Congratz-to-the-following-winners-of-the-KingsLeague-giveaway-YOmZ7cfZ9nqFu09-astro_pixell-Mis_iggyminaj",
            "created_at": "2023-07-10T14:51:06Z",
            "votes": {
                "negative": 0,
                "positive": 0,
                "important": 0,
                "liked": 0,
                "disliked": 0,
                "lol": 0,
                "toxic": 0,
                "saved": 0,
                "comments": 0
            }
        },
        {
            "kind": "news",
            "domain": "@RealFlokiInu",
            "source": {
                "title": "Floki Inu Twitter",
                "region": "en",
                "domain": "twitter.com",
                "path": "@realflokiinu"
            },
            "title": "RT @bsc_daily:  Booking 600+ Airline with @RealFlokiInu $FLOKI \n\nUsers Can Use $FLOKI Token on Alternative Airlines via @binance Pay Now\u2026",
            "published_at": "2023-07-10T14:23:37Z",
            "slug": "RT-bsc_daily-Booking-600-Airline-with-RealFlokiInu-FLOKI-Users-Can-Use-FLOKI-Token-on-Alternative-Airlines-via-binance-Pay-Now",
            "currencies": [
                {
                    "code": "FLOKI",
                    "title": "Floki Inu",
                    "slug": null,
                    "url": "https:\/\/cryptopanic.com\/news\/None\/"
                },
                {
                    "code": "FLOKI",
                    "title": "FLOKI",
                    "slug": "floki",
                    "url": "https:\/\/cryptopanic.com\/news\/floki\/"
                }
            ],
            "id": 18756186,
            "url": "https:\/\/cryptopanic.com\/news\/18756186\/RT-bsc_daily-Booking-600-Airline-with-RealFlokiInu-FLOKI-Users-Can-Use-FLOKI-Token-on-Alternative-Airlines-via-binance-Pay-Now",
            "created_at": "2023-07-10T14:23:37Z",
            "votes": {
                "negative": 0,
                "positive": 0,
                "important": 0,
                "liked": 0,
                "disliked": 0,
                "lol": 0,
                "toxic": 0,
                "saved": 0,
                "comments": 0
            }
        },
        {
            "kind": "news",
            "domain": "@RealFlokiInu",
            "source": {
                "title": "Floki Inu Twitter",
                "region": "en",
                "domain": "twitter.com",
                "path": "@realflokiinu"
            },
            "title": "Rise and shine, Vikings! Let's start the week fresh at #Valhalla's waterfall. \n\nWash away the weekend fun and gear\u2026",
            "published_at": "2023-07-10T10:59:14Z",
            "slug": "Rise-and-shine-Vikings-Lets-start-the-week-fresh-at-Valhallas-waterfall-Wash-away-the-weekend-fun-and-gear",
            "currencies": [
                {
                    "code": "FLOKI",
                    "title": "Floki Inu",
                    "slug": null,
                    "url": "https:\/\/cryptopanic.com\/news\/None\/"
                },
                {
                    "code": "FLOKI",
                    "title": "FLOKI",
                    "slug": "floki",
                    "url": "https:\/\/cryptopanic.com\/news\/floki\/"
                }
            ],
            "id": 18756187,
            "url": "https:\/\/cryptopanic.com\/news\/18756187\/Rise-and-shine-Vikings-Lets-start-the-week-fresh-at-Valhallas-waterfall-Wash-away-the-weekend-fun-and-gear",
            "created_at": "2023-07-10T10:59:14Z",
            "votes": {
                "negative": 0,
                "positive": 0,
                "important": 0,
                "liked": 0,
                "disliked": 0,
                "lol": 0,
                "toxic": 0,
                "saved": 0,
                "comments": 0
            }
        },
        {
            "kind": "news",
            "domain": "@RealFlokiInu",
            "source": {
                "title": "Floki Inu Twitter",
                "region": "en",
                "domain": "twitter.com",
                "path": "@realflokiinu"
            },
            "title": "RT @bsc_daily:  @RealFlokiInu Partnership with @BitGo \ud83e\udd1d\n\n#BitGo - a leading digital asset financial services provider &amp; #crypto custody so\u2026",
            "published_at": "2023-07-09T09:30:08Z",
            "slug": "RT-bsc_daily-RealFlokiInu-Partnership-with-BitGo-BitGo-a-leading-digital-asset-financial-services-provider-amp-crypto-custody-so",
            "currencies": [
                {
                    "code": "FLOKI",
                    "title": "Floki Inu",
                    "slug": null,
                    "url": "https:\/\/cryptopanic.com\/news\/None\/"
                },
                {
                    "code": "FLOKI",
                    "title": "FLOKI",
                    "slug": "floki",
                    "url": "https:\/\/cryptopanic.com\/news\/floki\/"
                }
            ],
            "id": 18749714,
            "url": "https:\/\/cryptopanic.com\/news\/18749714\/RT-bsc_daily-RealFlokiInu-Partnership-with-BitGo-BitGo-a-leading-digital-asset-financial-services-provider-amp-crypto-custody-so",
            "created_at": "2023-07-09T09:30:08Z",
            "votes": {
                "negative": 0,
                "positive": 0,
                "important": 0,
                "liked": 0,
                "disliked": 0,
                "lol": 0,
                "toxic": 0,
                "saved": 0,
                "comments": 0
            }
        },
        {
            "kind": "news",
            "domain": "@RealFlokiInu",
            "source": {
                "title": "Floki Inu Twitter",
                "region": "en",
                "domain": "twitter.com",
                "path": "@realflokiinu"
            },
            "title": "RT @ShopFloki: Join the #FLOKI fashion parade and let your style be featured!\n\n1. Put on your favorite merch from",
            "published_at": "2023-07-08T16:30:36Z",
            "slug": "RT-ShopFloki-Join-the-FLOKI-fashion-parade-and-let-your-style-be-featured-1-Put-on-your-favorite-merch-from",
            "currencies": [
                {
                    "code": "FLOKI",
                    "title": "Floki Inu",
                    "slug": null,
                    "url": "https:\/\/cryptopanic.com\/news\/None\/"
                },
                {
                    "code": "FLOKI",
                    "title": "FLOKI",
                    "slug": "floki",
                    "url": "https:\/\/cryptopanic.com\/news\/floki\/"
                }
            ],
            "id": 18745535,
            "url": "https:\/\/cryptopanic.com\/news\/18745535\/RT-ShopFloki-Join-the-FLOKI-fashion-parade-and-let-your-style-be-featured-1-Put-on-your-favorite-merch-from",
            "created_at": "2023-07-08T16:30:36Z",
            "votes": {
                "negative": 0,
                "positive": 0,
                "important": 0,
                "liked": 0,
                "disliked": 0,
                "lol": 0,
                "toxic": 0,
                "saved": 0,
                "comments": 0
            }
        },
        {
            "kind": "news",
            "domain": "@RealFlokiInu",
            "source": {
                "title": "Floki Inu Twitter",
                "region": "en",
                "domain": "twitter.com",
                "path": "@realflokiinu"
            },
            "title": "Last night, we hosted a #Floki Singing Contest in our Telegram VC, and it turned out to be an incredible event!\n\nCh\u2026",
            "published_at": "2023-07-08T14:08:45Z",
            "slug": "Last-night-we-hosted-a-Floki-Singing-Contest-in-our-Telegram-VC-and-it-turned-out-to-be-an-incredible-event-Ch",
            "currencies": [
                {
                    "code": "FLOKI",
                    "title": "Floki Inu",
                    "slug": null,
                    "url": "https:\/\/cryptopanic.com\/news\/None\/"
                },
                {
                    "code": "FLOKI",
                    "title": "FLOKI",
                    "slug": "floki",
                    "url": "https:\/\/cryptopanic.com\/news\/floki\/"
                }
            ],
            "id": 18745536,
            "url": "https:\/\/cryptopanic.com\/news\/18745536\/Last-night-we-hosted-a-Floki-Singing-Contest-in-our-Telegram-VC-and-it-turned-out-to-be-an-incredible-event-Ch",
            "created_at": "2023-07-08T14:08:45Z",
            "votes": {
                "negative": 0,
                "positive": 0,
                "important": 0,
                "liked": 0,
                "disliked": 0,
                "lol": 0,
                "toxic": 0,
                "saved": 0,
                "comments": 0
            }
        },
        {
            "kind": "news",
            "domain": "@RealFlokiInu",
            "source": {
                "title": "Floki Inu Twitter",
                "region": "en",
                "domain": "twitter.com",
                "path": "@realflokiinu"
            },
            "title": "$FLOKI is back at it again, turning trending on Twitter into a daily ritual! \n\n#FLOKI is trending with 3.1 million\u2026",
            "published_at": "2023-07-08T12:08:06Z",
            "slug": "FLOKI-is-back-at-it-again-turning-trending-on-Twitter-into-a-daily-ritual-FLOKI-is-trending-with-31-million",
            "currencies": [
                {
                    "code": "FLOKI",
                    "title": "Floki Inu",
                    "slug": null,
                    "url": "https:\/\/cryptopanic.com\/news\/None\/"
                },
                {
                    "code": "FLOKI",
                    "title": "FLOKI",
                    "slug": "floki",
                    "url": "https:\/\/cryptopanic.com\/news\/floki\/"
                }
            ],
            "id": 18745537,
            "url": "https:\/\/cryptopanic.com\/news\/18745537\/FLOKI-is-back-at-it-again-turning-trending-on-Twitter-into-a-daily-ritual-FLOKI-is-trending-with-31-million",
            "created_at": "2023-07-08T12:08:06Z",
            "votes": {
                "negative": 0,
                "positive": 0,
                "important": 0,
                "liked": 0,
                "disliked": 0,
                "lol": 0,
                "toxic": 0,
                "saved": 0,
                "comments": 0
            }
        },
        {
            "kind": "news",
            "domain": "@RealFlokiInu",
            "source": {
                "title": "Floki Inu Twitter",
                "region": "en",
                "domain": "twitter.com",
                "path": "@realflokiinu"
            },
            "title": "#Floki's singing contest has started!\n\nJoin our voice chat at to join the fun!",
            "published_at": "2023-07-07T18:02:27Z",
            "slug": "Flokis-singing-contest-has-started-Join-our-voice-chat-at-to-join-the-fun",
            "currencies": [
                {
                    "code": "FLOKI",
                    "title": "Floki Inu",
                    "slug": null,
                    "url": "https:\/\/cryptopanic.com\/news\/None\/"
                },
                {
                    "code": "FLOKI",
                    "title": "FLOKI",
                    "slug": "floki",
                    "url": "https:\/\/cryptopanic.com\/news\/floki\/"
                }
            ],
            "id": 18740160,
            "url": "https:\/\/cryptopanic.com\/news\/18740160\/Flokis-singing-contest-has-started-Join-our-voice-chat-at-to-join-the-fun",
            "created_at": "2023-07-07T18:02:27Z",
            "votes": {
                "negative": 0,
                "positive": 0,
                "important": 0,
                "liked": 0,
                "disliked": 0,
                "lol": 0,
                "toxic": 0,
                "saved": 0,
                "comments": 0
            }
        },
        {
            "kind": "news",
            "domain": "@RealFlokiInu",
            "source": {
                "title": "Floki Inu Twitter",
                "region": "en",
                "domain": "twitter.com",
                "path": "@realflokiinu"
            },
            "title": "RT @bsc_daily:  @RealFlokiInu Has Crossed 400,000 Holders on @BNBCHAIN \n\nIn addition, #Floki has 72,900 holders on the $ETH chain, bringi\u2026",
            "published_at": "2023-07-07T16:52:42Z",
            "slug": "RT-bsc_daily-RealFlokiInu-Has-Crossed-400000-Holders-on-BNBCHAIN-In-addition-Floki-has-72900-holders-on-the-ETH-chain-bringi",
            "currencies": [
                {
                    "code": "FLOKI",
                    "title": "Floki Inu",
                    "slug": null,
                    "url": "https:\/\/cryptopanic.com\/news\/None\/"
                },
                {
                    "code": "FLOKI",
                    "title": "FLOKI",
                    "slug": "floki",
                    "url": "https:\/\/cryptopanic.com\/news\/floki\/"
                }
            ],
            "id": 18740161,
            "url": "https:\/\/cryptopanic.com\/news\/18740161\/RT-bsc_daily-RealFlokiInu-Has-Crossed-400000-Holders-on-BNBCHAIN-In-addition-Floki-has-72900-holders-on-the-ETH-chain-bringi",
            "created_at": "2023-07-07T16:52:42Z",
            "votes": {
                "negative": 0,
                "positive": 0,
                "important": 0,
                "liked": 0,
                "disliked": 0,
                "lol": 0,
                "toxic": 0,
                "saved": 0,
                "comments": 0
            }
        },
        {
            "kind": "news",
            "domain": "@RealFlokiInu",
            "source": {
                "title": "Floki Inu Twitter",
                "region": "en",
                "domain": "twitter.com",
                "path": "@realflokiinu"
            },
            "title": "#Floki Weekly Recap \ufe0f\n\nMissed any of $FLOKI's news &amp; updates? We have you covered!\n\nHop on Spaces with us to discu\u2026",
            "published_at": "2023-07-07T15:22:58Z",
            "slug": "Floki-Weekly-Recap-Missed-any-of-FLOKIs-news-amp-updates-We-have-you-covered-Hop-on-Spaces-with-us-to-discu",
            "currencies": [
                {
                    "code": "FLOKI",
                    "title": "Floki Inu",
                    "slug": null,
                    "url": "https:\/\/cryptopanic.com\/news\/None\/"
                },
                {
                    "code": "FLOKI",
                    "title": "FLOKI",
                    "slug": "floki",
                    "url": "https:\/\/cryptopanic.com\/news\/floki\/"
                }
            ],
            "id": 18740162,
            "url": "https:\/\/cryptopanic.com\/news\/18740162\/Floki-Weekly-Recap-Missed-any-of-FLOKIs-news-amp-updates-We-have-you-covered-Hop-on-Spaces-with-us-to-discu",
            "created_at": "2023-07-07T15:22:58Z",
            "votes": {
                "negative": 0,
                "positive": 0,
                "important": 0,
                "liked": 0,
                "disliked": 0,
                "lol": 0,
                "toxic": 0,
                "saved": 0,
                "comments": 0
            }
        },
        {
            "kind": "news",
            "domain": "@RealFlokiInu",
            "source": {
                "title": "Floki Inu Twitter",
                "region": "en",
                "domain": "twitter.com",
                "path": "@realflokiinu"
            },
            "title": "$FLOKI and @FlokiFi are both audited by leading blockchain security partner @CertiK",
            "published_at": "2023-07-07T11:58:16Z",
            "slug": "FLOKI-and-FlokiFi-are-both-audited-by-leading-blockchain-security-partner-CertiK",
            "currencies": [
                {
                    "code": "FLOKI",
                    "title": "Floki Inu",
                    "slug": null,
                    "url": "https:\/\/cryptopanic.com\/news\/None\/"
                },
                {
                    "code": "FLOKI",
                    "title": "FLOKI",
                    "slug": "floki",
                    "url": "https:\/\/cryptopanic.com\/news\/floki\/"
                }
            ],
            "id": 18740163,
            "url": "https:\/\/cryptopanic.com\/news\/18740163\/FLOKI-and-FlokiFi-are-both-audited-by-leading-blockchain-security-partner-CertiK",
            "created_at": "2023-07-07T11:58:16Z",
            "votes": {
                "negative": 0,
                "positive": 0,
                "important": 0,
                "liked": 0,
                "disliked": 0,
                "lol": 0,
                "toxic": 0,
                "saved": 0,
                "comments": 0
            }
        },
        {
            "kind": "news",
            "domain": "@RealFlokiInu",
            "source": {
                "title": "Floki Inu Twitter",
                "region": "en",
                "domain": "twitter.com",
                "path": "@realflokiinu"
            },
            "title": "#Floki Viking Weekend Poll!\ufe0f\n\nWhat are your weekend plans?",
            "published_at": "2023-07-07T10:20:21Z",
            "slug": "Floki-Viking-Weekend-Poll-What-are-your-weekend-plans",
            "currencies": [
                {
                    "code": "FLOKI",
                    "title": "Floki Inu",
                    "slug": null,
                    "url": "https:\/\/cryptopanic.com\/news\/None\/"
                },
                {
                    "code": "FLOKI",
                    "title": "FLOKI",
                    "slug": "floki",
                    "url": "https:\/\/cryptopanic.com\/news\/floki\/"
                }
            ],
            "id": 18740164,
            "url": "https:\/\/cryptopanic.com\/news\/18740164\/Floki-Viking-Weekend-Poll-What-are-your-weekend-plans",
            "created_at": "2023-07-07T10:20:21Z",
            "votes": {
                "negative": 0,
                "positive": 0,
                "important": 0,
                "liked": 0,
                "disliked": 0,
                "lol": 0,
                "toxic": 0,
                "saved": 0,
                "comments": 0
            }
        },
        {
            "kind": "news",
            "domain": "@RealFlokiInu",
            "source": {
                "title": "Floki Inu Twitter",
                "region": "en",
                "domain": "twitter.com",
                "path": "@realflokiinu"
            },
            "title": "RT @WazirXIndia: $FLOKI | $SHIB | $DOGE | $PEPE\n\nWhich meme coin are you most bullish on?",
            "published_at": "2023-07-07T07:02:30Z",
            "slug": "RT-WazirXIndia-FLOKI-SHIB-DOGE-PEPE-Which-meme-coin-are-you-most-bullish-on",
            "currencies": [
                {
                    "code": "FLOKI",
                    "title": "Floki Inu",
                    "slug": null,
                    "url": "https:\/\/cryptopanic.com\/news\/None\/"
                },
                {
                    "code": "FLOKI",
                    "title": "FLOKI",
                    "slug": "floki",
                    "url": "https:\/\/cryptopanic.com\/news\/floki\/"
                },
                {
                    "code": "DOGE",
                    "title": "Dogecoin",
                    "slug": "dogecoin",
                    "url": "https:\/\/cryptopanic.com\/news\/dogecoin\/"
                },
                {
                    "code": "SHIB",
                    "title": "Shiba Inu",
                    "slug": "shiba-inu",
                    "url": "https:\/\/cryptopanic.com\/news\/shiba-inu\/"
                }
            ],
            "id": 18732506,
            "url": "https:\/\/cryptopanic.com\/news\/18732506\/RT-WazirXIndia-FLOKI-SHIB-DOGE-PEPE-Which-meme-coin-are-you-most-bullish-on",
            "created_at": "2023-07-07T07:02:30Z",
            "votes": {
                "negative": 0,
                "positive": 0,
                "important": 0,
                "liked": 0,
                "disliked": 0,
                "lol": 0,
                "toxic": 0,
                "saved": 0,
                "comments": 0
            }
        },
        {
            "kind": "news",
            "domain": "@RealFlokiInu",
            "source": {
                "title": "Floki Inu Twitter",
                "region": "en",
                "domain": "twitter.com",
                "path": "@realflokiinu"
            },
            "title": "Beware of fake $FLOKI Twitter pages with airdrop messages. They are SCAMS!\n\n#FLOKI is NOT conducting any airdrops a\u2026",
            "published_at": "2023-07-06T15:28:08Z",
            "slug": "Beware-of-fake-FLOKI-Twitter-pages-with-airdrop-messages-They-are-SCAMS-FLOKI-is-NOT-conducting-any-airdrops-a",
            "currencies": [
                {
                    "code": "FLOKI",
                    "title": "Floki Inu",
                    "slug": null,
                    "url": "https:\/\/cryptopanic.com\/news\/None\/"
                },
                {
                    "code": "FLOKI",
                    "title": "FLOKI",
                    "slug": "floki",
                    "url": "https:\/\/cryptopanic.com\/news\/floki\/"
                }
            ],
            "id": 18732507,
            "url": "https:\/\/cryptopanic.com\/news\/18732507\/Beware-of-fake-FLOKI-Twitter-pages-with-airdrop-messages-They-are-SCAMS-FLOKI-is-NOT-conducting-any-airdrops-a",
            "created_at": "2023-07-06T15:28:08Z",
            "votes": {
                "negative": 0,
                "positive": 0,
                "important": 0,
                "liked": 0,
                "disliked": 0,
                "lol": 0,
                "toxic": 0,
                "saved": 0,
                "comments": 0
            }
        },
        {
            "kind": "news",
            "domain": "@RealFlokiInu",
            "source": {
                "title": "Floki Inu Twitter",
                "region": "en",
                "domain": "twitter.com",
                "path": "@realflokiinu"
            },
            "title": "RT @BNBSwap:  @RealFlokiInu partners with @BitGo, a leading digital asset financial services provider &amp; #crypto custody solution with over\u2026",
            "published_at": "2023-07-06T14:43:48Z",
            "slug": "RT-BNBSwap-RealFlokiInu-partners-with-BitGo-a-leading-digital-asset-financial-services-provider-amp-crypto-custody-solution-with-over",
            "currencies": [
                {
                    "code": "FLOKI",
                    "title": "Floki Inu",
                    "slug": null,
                    "url": "https:\/\/cryptopanic.com\/news\/None\/"
                },
                {
                    "code": "FLOKI",
                    "title": "FLOKI",
                    "slug": "floki",
                    "url": "https:\/\/cryptopanic.com\/news\/floki\/"
                }
            ],
            "id": 18732508,
            "url": "https:\/\/cryptopanic.com\/news\/18732508\/RT-BNBSwap-RealFlokiInu-partners-with-BitGo-a-leading-digital-asset-financial-services-provider-amp-crypto-custody-solution-with-over",
            "created_at": "2023-07-06T14:43:48Z",
            "votes": {
                "negative": 0,
                "positive": 0,
                "important": 0,
                "liked": 0,
                "disliked": 0,
                "lol": 0,
                "toxic": 0,
                "saved": 0,
                "comments": 0
            }
        }
    ]
}
